<archetype xmlns="http://maven.apache.org/plugins/maven-archetype-plugin/archetype/1.0.0" xmlns:xsi="http://www.w3.org/2001/XMLSchema-instance"
  xsi:schemaLocation="http://maven.apache.org/plugins/maven-archetype-plugin/archetype/1.0.0 http://maven.apache.org/xsd/archetype-1.0.0.xsd">
  <!-- Must be the same as the pom's artifact ID -->
  <id>oaqa-archetype</id>
  <!-- Allows maven-ization of existing projects using this archetype -->
  <allowPartial>true</allowPartial>
  <!-- Default locations -->
  <sources>
    <source>src/main/java</source>
  </sources>
  <resources>
  	<resource>src/main/resources</resource>
  </resources>
  <testSources>
    <source>src/test/java</source>
  </testSources>
  <testResources>
    <resource>src/test/resources</resource>
  </testResources>
</archetype>